set_ings/__init__.py
set_ings/__version__.py
set_ings/exceptions.py
set_ings/settings.py
python_set_ings-0.2.2.dist-info/LICENSE
python_set_ings-0.2.2.dist-info/METADATA
python_set_ings-0.2.2.dist-info/WHEEL
python_set_ings-0.2.2.dist-info/top_level.txt
python_set_ings-0.2.2.dist-info/RECORD
